forked/__init__.py
forked/build.py
forked/cli.py
forked/config.py
forked/conflicts.py
forked/gitutil.py
forked/guards.py
forked/resolver.py
forked/sync.py
forked-0.0.2.dist-info/METADATA
forked-0.0.2.dist-info/WHEEL
forked-0.0.2.dist-info/entry_points.txt
forked-0.0.2.dist-info/licenses/LICENSE
forked-0.0.2.dist-info/RECORD
