Metadata-Version: 2.4
Name: forked
Version: 0.0.2
Summary: Git-native fork overlay & guard tool
License: MIT
License-File: LICENSE
Keywords: git,cli,fork,rebasing,automation
Author: Spenquatch
Author-email: spmcconnell.totaltele@gmail.com
Requires-Python: >=3.10
Classifier: Development Status :: 4 - Beta
Classifier: Intended Audience :: Developers
Classifier: License :: OSI Approved :: MIT License
Classifier: Programming Language :: Python
Classifier: Programming Language :: Python :: 3
Classifier: Programming Language :: Python :: 3.10
Classifier: Programming Language :: Python :: 3.11
Classifier: Programming Language :: Python :: 3.12
Classifier: Operating System :: OS Independent
Classifier: Topic :: Software Development :: Version Control
Requires-Dist: pathspec (>=0.12)
Requires-Dist: pyyaml (>=6.0)
Requires-Dist: rich (>=13.7)
Requires-Dist: typer (>=0.12)
Project-URL: Documentation, https://github.com/Spenquatch/fork#readme
Project-URL: Issues, https://github.com/Spenquatch/fork/issues
Project-URL: Repository, https://github.com/Spenquatch/fork
